setup.py
pkg2pypm/__init__.py
pkg2pypm/info.py
pkg2pypm.egg-info/PKG-INFO
pkg2pypm.egg-info/SOURCES.txt
pkg2pypm.egg-info/dependency_links.txt
pkg2pypm.egg-info/entry_points.txt
pkg2pypm.egg-info/requires.txt
pkg2pypm.egg-info/top_level.txt
pkg2pypm.egg-info/zip-safe