Metadata-Version: 1.0
Name: pkg2pypm
Version: 0.1.21
Summary: pkg2pypm v. 0.1.21
